{"cameraMode":{"drawMode":0,"name":"Shaded","section":"Shading Mode"},"sceneLighting":true,"audioPlay":false,"sceneViewState":{"m_AlwaysRefresh":false,"showFog":true,"showSkybox":true,"showFlares":true,"showImageEffects":true,"showParticleSystems":true,"showVisualEffectGraphs":true,"m_FxEnabled":true},"in2DMode":false,"pivot":{"x":17.483610153198243,"y":11.82862663269043,"z":4.164830684661865},"rotation":{"x":-0.07285623252391815,"y":0.7327221035957336,"z":-0.07944387942552567,"w":-0.6719837188720703},"size":8.399438858032227,"orthographic":false}